LICENSE
README.md
pyproject.toml
setup.py
genome_tools/__init__.py
genome_tools/__main__.py
genome_tools/bed.py
genome_tools/genomic_interval.py
genome_tools/helpers.py
genome_tools.egg-info/PKG-INFO
genome_tools.egg-info/SOURCES.txt
genome_tools.egg-info/dependency_links.txt
genome_tools.egg-info/not-zip-safe
genome_tools.egg-info/requires.txt
genome_tools.egg-info/top_level.txt
genome_tools/cli/__init__.py
genome_tools/data/__init__.py
genome_tools/data/anndata.py
genome_tools/data/dataset.py
genome_tools/data/extractors.py
genome_tools/data/gc_matching.py
genome_tools/data/loaders.py
genome_tools/data/samplers.py
genome_tools/data/utils.py
genome_tools/plotting/__init__.py
genome_tools/plotting/connectors.py
genome_tools/plotting/gene_annotation.py
genome_tools/plotting/ideogram.py
genome_tools/plotting/pwm.py
genome_tools/plotting/sequence.py
genome_tools/plotting/utils.py
genome_tools/plotting/colors/__init__.py
genome_tools/plotting/colors/cm.py
genome_tools/plotting/colors/palettes.py
genome_tools/utils/__init__.py
genome_tools/utils/sampling.py
genome_tools/utils/sequence.py
genome_tools/utils/signal.py