Metadata-Version: 2.1
Name: genome-tools
Version: 2.0.0
Summary: A toolkit for genome analysis and manipulation.
Download-URL: https://github.com/jvierstra/genome-tools/archive/v2.0.0.tar.gz
Author: Jeff Vierstra
Author-email: Jeff Vierstra <jvierstra@altius.org>
License:                     GNU GENERAL PUBLIC LICENSE
Project-URL: Homepage, https://github.com/vierstralab/genome-tools
Project-URL: Repository, https://github.com/vierstralab/genome-tools
Project-URL: Issues, https://github.com/vierstralab/genome-tools/issues
Keywords: genome,bioinformatics,analysis,toolkit
Requires-Python: >=3.8
Requires-Dist: numpy
Requires-Dist: pandas
Requires-Dist: pysam
Requires-Dist: pyBigWig
Requires-Dist: matplotlib
Requires-Dist: descartes
Requires-Dist: fonttools==4.49.0
Requires-Dist: openpyxl
Requires-Dist: shapely
